jps_crontab_utils/__init__.py
jps_crontab_utils/check_crontab.py
jps_crontab_utils/parser.py
jps_crontab_utils/search_crontab.py
jps_crontab_utils/utils.py
jps_crontab_utils-0.1.0.dist-info/licenses/LICENSE
jps_crontab_utils-0.1.0.dist-info/METADATA
jps_crontab_utils-0.1.0.dist-info/WHEEL
jps_crontab_utils-0.1.0.dist-info/entry_points.txt
jps_crontab_utils-0.1.0.dist-info/top_level.txt
jps_crontab_utils-0.1.0.dist-info/RECORD
